Metadata-Version: 2.2
Name: qurro
Version: 0.9.0
Summary: Visualizes differentially ranked features and log-ratios of their sample abundances
Home-page: https://github.com/biocore/qurro
Author: Qurro development team
Author-email: mfedarko@ucsd.edu
Maintainer: Qurro development team
Maintainer-email: mfedarko@ucsd.edu
License: BSD
Classifier: Development Status :: 3 - Alpha
Classifier: License :: OSI Approved :: BSD License
Classifier: Topic :: Scientific/Engineering
Classifier: Topic :: Scientific/Engineering :: Bio-Informatics
Classifier: Topic :: Scientific/Engineering :: Visualization
Classifier: Programming Language :: Python :: 3.6
Classifier: Programming Language :: Python :: 3.7
Classifier: Programming Language :: Python :: 3.8
Classifier: Programming Language :: Python :: 3.9
Classifier: Programming Language :: Python :: 3.10
Classifier: Programming Language :: Python :: 3.12
Classifier: Programming Language :: Python :: 3.13
Classifier: Programming Language :: Python :: 3 :: Only
Classifier: Operating System :: Unix
Classifier: Operating System :: POSIX
Classifier: Operating System :: MacOS :: MacOS X
Requires-Python: >=3.6
License-File: LICENSE.txt
Requires-Dist: altair>=4.0
Requires-Dist: biom-format[hdf5]>=2.1.9
Requires-Dist: click
Requires-Dist: numpy>=1.12.0
Requires-Dist: pandas>=1
Requires-Dist: scikit-bio>0.5.3
Requires-Dist: scipy>=1.3.0
Provides-Extra: dev
Requires-Dist: pytest>=4.2; extra == "dev"
Requires-Dist: pytest-cov>=2.0; extra == "dev"
Requires-Dist: flake8; extra == "dev"
Requires-Dist: nbconvert; extra == "dev"
Dynamic: author
Dynamic: author-email
Dynamic: classifier
Dynamic: description
Dynamic: description-content-type
Dynamic: home-page
Dynamic: license
Dynamic: maintainer
Dynamic: maintainer-email
Dynamic: provides-extra
Dynamic: requires-dist
Dynamic: requires-python
Dynamic: summary
